MANIFEST.in
README.txt
setup.cfg
setup.py
tw2/__init__.py
tw2.devtools.egg-info/PKG-INFO
tw2.devtools.egg-info/SOURCES.txt
tw2.devtools.egg-info/dependency_links.txt
tw2.devtools.egg-info/entry_points.txt
tw2.devtools.egg-info/namespace_packages.txt
tw2.devtools.egg-info/not-zip-safe
tw2.devtools.egg-info/requires.txt
tw2.devtools.egg-info/top_level.txt
tw2/devtools/__init__.py
tw2/devtools/browser.py
tw2/devtools/browser_config.ini
tw2/devtools/memoize.py
tw2/devtools/paste_template.py
tw2/devtools/rststub.txt
tw2/devtools/server.py
tw2/devtools/tabs.py
tw2/devtools/static/css/core.css
tw2/devtools/static/css/grid.css
tw2/devtools/static/css/pygments.css
tw2/devtools/static/css/reset.css
tw2/devtools/static/css/tosca.css
tw2/devtools/static/images/backshadow-left.png
tw2/devtools/static/images/backshadow-right.png
tw2/devtools/static/images/disclosure-closed.png
tw2/devtools/static/images/disclosure-opened.png
tw2/devtools/static/images/favicon.ico
tw2/devtools/static/images/header-bg-dark.jpg
tw2/devtools/static/images/header-bg.jpg
tw2/devtools/static/images/toscawidgets-icon.jpg
tw2/devtools/static/images/toscawidgets-logo.jpg
tw2/devtools/static/js/jquery.scrollTo-1.4.2-min.js
tw2/devtools/static/js/less-1.2.1.min.js
tw2/devtools/static/js/prefixfree.min.js
tw2/devtools/static/js/source.js
tw2/devtools/static/js/lib/jquery-1.7.1.min.js
tw2/devtools/static/js/lib/less-1.2.1.min.js
tw2/devtools/static/js/lib/prefixfree.min.js
tw2/devtools/static/js/visua/core.js
tw2/devtools/static/old/bullet.gif
tw2/devtools/static/old/favicon.ico
tw2/devtools/static/old/header-bg.jpg
tw2/devtools/static/old/icon-header.jpg
tw2/devtools/static/old/pygments.css
tw2/devtools/static/old/tosca.css
tw2/devtools/static/old/toscawidgets-logo.jpg
tw2/devtools/static/old/js/browser.js
tw2/devtools/static/old/js/jquery-1.4.3.min.js
tw2/devtools/static/old/js/source.js
tw2/devtools/templates/__init__.py
tw2/devtools/templates/__init__.pyc
tw2/devtools/templates/wb_module.html
tw2/devtools/templates/wb_page.html
tw2/devtools/templates/wb_validator.html
tw2/devtools/templates/wb_welcome.html
tw2/devtools/templates/wb_widget.html
tw2/devtools/templates/__pycache__/__init__.cpython-33.pyc
tw2/paste_templates/__init__.py
tw2/paste_templates/__init__.pyc
