Metadata-Version: 1.1
Name: tw2.devtools
Version: 2.2.0.2
Summary: The development tools for ToscaWidgets 2, a web widget toolkit.
Home-page: http://toscawidgets.org/
Author: Paul Johnston, Christopher Perkins, Alberto Valverde Gonzalez & contributors
Author-email: toscawidgets-discuss@googlegroups.com
License: MIT
Download-URL: https://pypi.python.org/pypi/tw2.devtools/
Platform: UNKNOWN
Classifier: Development Status :: 3 - Alpha
Classifier: Environment :: Web Environment
Classifier: Environment :: Web Environment :: ToscaWidgets
Classifier: Topic :: Software Development :: Libraries :: Python Modules
Classifier: Topic :: Internet :: WWW/HTTP :: WSGI
Classifier: Topic :: Internet :: WWW/HTTP :: WSGI :: Middleware
Classifier: Topic :: Software Development :: Widget Sets
Classifier: Intended Audience :: Developers
Classifier: License :: OSI Approved :: MIT License
Classifier: Operating System :: OS Independent
Classifier: Programming Language :: Python
